Workbook

Sheet orders
A1: Order ID | B1: Order Date | C1: Customer ID | D1: Product ID | E1: Quantity | F1: Customer Name | G1: Email | H1: Country | I1: Coffee Type | J1: Roast Type | K1: Size | L1: Unit Price | M1: Sales
A2: QEV-37451-860 | B2: 43713 | C2: 17670-51384-MA | D2: R-M-1 | E2: 2
A3: QEV-37451-860 | B3: 43713 | C3: 17670-51384-MA | D3: E-M-0.5 | E3: 5
A4: FAA-43335-268 | B4: 44364 | C4: 21125-22134-PX | D4: A-L-1 | E4: 1
A5: KAC-83089-793 | B5: 44392 | C5: 23806-46781-OU | D5: E-M-1 | E5: 2
A6: KAC-83089-793 | B6: 44392 | C6: 23806-46781-OU | D6: R-L-2.5 | E6: 2
A7: CVP-18956-553 | B7: 44412 | C7: 86561-91660-RB | D7: L-D-1 | E7: 3
A8: IPP-31994-879 | B8: 44582 | C8: 65223-29612-CB | D8: E-D-0.5 | E8: 3
A9: SNZ-65340-705 | B9: 44701 | C9: 21134-81676-FR | D9: L-L-0.2 | E9: 1
A10: EZT-46571-659 | B10: 43467 | C10: 03396-68805-ZC | D10: R-M-0.5 | E10: 3
A11: NWQ-70061-912 | B11: 43713 | C11: 61021-27840-ZN | D11: R-M-0.5 | E11: 1
A12: BKK-47233-845 | B12: 44263 | C12: 76239-90137-UQ | D12: A-D-1 | E12: 4
A13: VQR-01002-970 | B13: 44132 | C13: 49315-21985-BB | D13: E-L-2.5 | E13: 5
... A1001: IRV-20769-219 | B1001: 44119 | C1001: 77131-58092-GE | D1001: E-M-0.2 | E1001: 3

Sheet customers
A1: Customer ID | B1: Customer Name | C1: Email | D1: Phone Number | E1: Address Line 1 | F1: City | G1: Country | H1: Postcode | I1: Loyalty Card
A2: 17670-51384-MA | B2: Aloisia Allner | C2: aallner0@lulu.com | D2: +1 (862) 817-0124 | E2: 57999 Pepper Wood Alley | F2: Paterson | G2: United States | H2: 7505 | I2: Yes
A3: 73342-18763-UW | B3: Piotr Bote | C3: pbote1@yelp.com | D3: +353 (913) 396-4653 | E3: 2112 Ridgeway Hill | F3: Crumlin | G3: Ireland | H3: D6W | I3: No
A4: 21125-22134-PX | B4: Jami Redholes | C4: jredholes2@tmall.com | D4: +1 (210) 986-6806 | E4: 5214 Bartillon Park | F4: San Antonio | G4: United States | H4: 78205 | I4: Yes
A5: 71253-00052-RN | B5: Dene Azema | C5: dazema3@facebook.com | D5: +1 (217) 418-0714 | E5: 27 Maywood Place | F5: Springfield | G5: United States | H5: 62711 | I5: Yes
A6: 23806-46781-OU | B6: Christoffer O' Shea | D6: +353 (698) 362-9201 | E6: 38980 Manitowish Junction | F6: Cill Airne | G6: Ireland | H6: N41 | I6: No
A7: 86561-91660-RB | B7: Beryle Cottier | D7: +1 (570) 289-7473 | E7: 2651 Stoughton Place | F7: Scranton | G7: United States | H7: 18505 | I7: No
A8: 65223-29612-CB | B8: Shaylynn Lobe | C8: slobe6@nifty.com | D8: +1 (937) 954-4541 | E8: 7005 Mariners Cove Place | F8: Dayton | G8: United States | H8: 45440 | I8: Yes
A9: 21134-81676-FR | B9: Melvin Wharfe | D9: +353 (507) 574-3034 | E9: 7 Straubel Road | F9: Kill | G9: Ireland | H9: P24 | I9: Yes
A10: 03396-68805-ZC | B10: Guthrey Petracci | C10: gpetracci8@livejournal.com | D10: +1 (310) 868-1842 | E10: 949 Paget Parkway | F10: Los Angeles | G10: United States | H10: 90045 | I10: No
A11: 61021-27840-ZN | B11: Rodger Raven | C11: rraven9@ed.gov | D11: +1 (213) 263-0288 | E11: 1 Reinke Avenue | F11: Los Angeles | G11: United States | H11: 90065 | I11: No
A12: 76239-90137-UQ | B12: Ferrell Ferber | C12: fferbera@businesswire.com | D12: +1 (408) 383-5302 | E12: 68 High Crossing Court | F12: San Jose | G12: United States | H12: 95160 | I12: No
A13: 49315-21985-BB | B13: Duky Phizackerly | C13: dphizackerlyb@utexas.edu | D13: +1 (408) 533-6012 | E13: 28643 Bluejay Crossing | F13: San Jose | G13: United States | H13: 95194 | I13: Yes
A14: 34136-36674-OM | B14: Rosaleen Scholar | C14: rscholarc@nyu.edu | D14: +1 (804) 420-0420 | E14: 80915 Montana Park | F14: Richmond | G14: United States | H14: 23285 | I14: No
A15: 39396-12890-PE | B15: Terence Vanyutin | C15: tvanyutind@wix.com | E15: 331 Bunting Hill | F15: Migrate | G15: United States | H15: 41905 | I15: No
A16: 95875-73336-RG | B16: Patrice Trobe | C16: ptrobee@wunderground.com | D16: +1 (314) 240-7896 | E16: 827 Declaration Plaza | F16: Saint Louis | G16: United States | H16: 63131 | I16: Yes
A17: 25473-43727-BY | B17: Llywellyn Oscroft | C17: loscroftf@ebay.co.uk | E17: 022 Roth Place | F17: Philadelphia | G17: United States | H17: 19172 | I17: No
A18: 99643-51048-IQ | B18: Minni Alabaster | C18: malabasterg@hexun.com | D18: +1 (971) 483-6255 | E18: 3 Charing Cross Trail | F18: Portland | G18: United States | H18: 97271 | I18: No
A19: 62173-15287-CU | B19: Rhianon Broxup | C19: rbroxuph@jimdo.com | D19: +1 (713) 663-1338 | E19: 83517 Thierer Court | F19: Houston | G19: United States | H19: 77240 | I19: No
A20: 57611-05522-ST | B20: Pall Redford | C20: predfordi@ow.ly | E20: 7337 Hayes Junction | F20: Caherconlish | G20: Ireland | H20: F45 | I20: Yes
A21: 76664-37050-DT | B21: Aurea Corradino | C21: acorradinoj@harvard.edu | D21: +1 (646) 202-5965 | E21: 698 Canary Terrace | F21: New York City | G21: United States | H21: 10060 | I21: Yes
A22: 84565-53984-SX | B22: Kendal Scardefield | D22: +353 (733) 405-3302 | E22: 3 Northridge Crossing | F22: Clondalkin | G22: Ireland | H22: D24 | I22: Yes
A23: 03090-88267-BQ | B23: Avrit Davidowsky | C23: adavidowskyl@netvibes.com | D23: +1 (616) 481-9962 | E23: 9 Warrior Junction | F23: Grand Rapids | G23: United States | H23: 49560 | I23: No
A24: 37651-47492-NC | B24: Annabel Antuk | C24: aantukm@kickstarter.com | D24: +1 (941) 740-6268 | E24: 77965 Lawn Park | F24: Punta Gorda | G24: United States | H24: 33982 | I24: Yes
A25: 95399-57205-HI | B25: Iorgo Kleinert | C25: ikleinertn@timesonline.co.uk | D25: +1 (360) 352-6598 | E25: 1 Morningstar Lane | F25: Vancouver | G25: United States | H25: 98682 | I25: Yes
A26: 24010-66714-HW | B26: Chrisy Blofeld | C26: cblofeldo@amazon.co.uk | D26: +1 (303) 936-3357 | E26: 013 Talisman Terrace | F26: Englewood | G26: United States | H26: 80150 | I26: No
A27: 07591-92789-UA | B27: Culley Farris | D27: +1 (941) 267-4822 | E27: 4 Mitchell Drive | F27: Punta Gorda | G27: United States | H27: 33982 | I27: Yes
A28: 49231-44455-IC | B28: Selene Shales | C28: sshalesq@umich.edu | D28: +1 (707) 881-5004 | E28: 74 Bultman Plaza | F28: Petaluma | G28: United States | H28: 94975 | I28: Yes
A29: 50124-88608-EO | B29: Vivie Danneil | C29: vdanneilr@mtv.com | D29: +353 (751) 346-0399 | E29: 5626 Darwin Avenue | F29: Tralee | G29: Ireland | H29: V92 | I29: No
A30: 00888-74814-UZ | B30: Theresita Newbury | C30: tnewburys@usda.gov | D30: +353 (803) 587-0026 | E30: 79526 Bultman Lane | F30: Clonskeagh | G30: Ireland | H30: D04 | I30: No
A31: 14158-30713-OB | B31: Mozelle Calcutt | C31: mcalcuttt@baidu.com | D31: +353 (928) 869-1762 | E31: 4389 Russell Way | F31: Rathwire | G31: Ireland | H31: Y25 | I31: Yes
A32: 51427-89175-QJ | B32: Adrian Swaine | D32: +1 (303) 486-9517 | E32: 95 Straubel Hill | F32: Aurora | G32: United States | H32: 80044 | I32: No
A33: 52082-49024-ON | B33: Ray Leivesley | C33: rleivesleyv@canalblog.com | D33: +1 (212) 535-7791 | E33: 91 Stephen Drive | F33: Jamaica | G33: United States | H33: 11407 | I33: No
A34: 04540-43685-DV | B34: Nelly Basezzi | C34: nbasezziw@webeden.co.uk | D34: +353 (125) 815-7345 | E34: 923 Mallard Junction | F34: Bailieborough | G34: Ireland | H34: C15 | I34: Yes
A35: 39123-12846-YJ | B35: Gallard Gatheral | C35: ggatheralx@123-reg.co.uk | E35: 40 Clemons Place | F35: Grand Forks | G35: United States | H35: 58207 | I35: No
A36: 44981-99666-XB | B36: Una Welberry | C36: uwelberryy@ebay.co.uk | D36: +44 (392) 503-8132 | E36: 40915 Schlimgen Park | F36: Upton | G36: United Kingdom | H36: DN21 | I36: Yes
A37: 24825-51803-CQ | B37: Faber Eilhart | C37: feilhartz@who.int | D37: +1 (304) 510-6095 | E37: 6966 Victoria Street | F37: Charleston | G37: United States | H37: 25362 | I37: No
A38: 77634-13918-GJ | B38: Zorina Ponting | C38: zponting10@altervista.org | D38: +1 (501) 172-1476 | E38: 7118 Holmberg Court | F38: Little Rock | G38: United States | H38: 72204 | I38: No
A39: 13694-25001-LX | B39: Silvio Strase | C39: sstrase11@booking.com | D39: +1 (303) 579-8015 | E39: 5 Forest Lane | F39: Denver | G39: United States | H39: 80291 | I39: No
A40: 08523-01791-TI | B40: Dorie de la Tremoille | C40: dde12@unesco.org | D40: +1 (612) 492-5160 | E40: 0817 Dennis Street | F40: Minneapolis | G40: United States | H40: 55458 | I40: No
A41: 49860-68865-AB | B41: Hy Zanetto | E41: 469 Paget Place | F41: Tucson | G41: United States | H41: 85715 | I41: Yes
A42: 21240-83132-SP | B42: Jessica McNess | D42: +1 (504) 545-1478 | E42: 664 Erie Place | F42: New Orleans | G42: United States | H42: 70116 | I42: No
A43: 08350-81623-TF | B43: Lorenzo Yeoland | C43: lyeoland15@pbs.org | D43: +1 (860) 576-2887 | E43: 8510 Merrick Road | F43: Hartford | G43: United States | H43: 6183 | I43: Yes
A44: 73284-01385-SJ | B44: Abigail Tolworthy | C44: atolworthy16@toplist.cz | D44: +1 (801) 722-4425 | E44: 74 Shopko Way | F44: Ogden | G44: United States | H44: 84409 | I44: Yes
A45: 04152-34436-IE | B45: Maurie Bartol | D45: +1 (617) 493-7594 | E45: 7625 Starling Court | F45: Boston | G45: United States | H45: 2216 | I45: No
A46: 06631-86965-XP | B46: Olag Baudassi | C46: obaudassi18@seesaa.net | D46: +1 (585) 356-6251 | E46: 55 Dottie Court | F46: Rochester | G46: United States | H46: 14604 | I46: Yes
A47: 54619-08558-ZU | B47: Petey Kingsbury | C47: pkingsbury19@comcast.net | D47: +1 (917) 705-8224 | E47: 28 Loftsgordon Place | F47: Bronx | G47: United States | H47: 10469 | I47: No
A48: 85589-17020-CX | B48: Donna Baskeyfied | D48: +1 (205) 923-1460 | E48: 7586 Logan Avenue | F48: Birmingham | G48: United States | H48: 35205 | I48: Yes
A49: 36078-91009-WU | B49: Arda Curley | C49: acurley1b@hao123.com | D49: +1 (760) 840-3808 | E49: 45098 Scott Drive | F49: San Bernardino | G49: United States | H49: 92415 | I49: Yes
A50: 15770-27099-GX | B50: Raynor McGilvary | C50: rmcgilvary1c@tamu.edu | E50: 496 Rockefeller Court | F50: Norfolk | G50: United States | H50: 23514 | I50: No
A51: 91460-04823-BX | B51: Isis Pikett | C51: ipikett1d@xinhuanet.com | D51: +1 (202) 871-9039 | E51: 5892 Hauk Drive | F51: Washington | G51: United States | H51: 20409 | I51: No
A52: 45089-52817-WN | B52: Inger Bouldon | C52: ibouldon1e@gizmodo.com | D52: +1 (754) 391-4736 | E52: 925 Barby Circle | F52: Fort Lauderdale | G52: United States | H52: 33355 | I52: No
A53: 76447-50326-IC | B53: Karry Flanders | C53: kflanders1f@over-blog.com | D53: +353 (467) 720-7274 | E53: 88 Blue Bill Park Avenue | F53: Crumlin | G53: Ireland | H53: D6W | I53: Yes
A54: 26333-67911-OL | B54: Hartley Mattioli | C54: hmattioli1g@webmd.com | E54: 126 Valley Edge Street | F54: Kinloch | G54: United Kingdom | H54: PH43 | I54: No
A55: 40768-49176-BL | B55: Horatio Rubberts | C55: hrubberts1h@google.com.hk | D55: +1 (801) 635-8791 | E55: 459 Russell Center | F55: Provo | G55: United States | H55: 84605 | I55: No
A56: 22107-86640-SB | B56: Archambault Gillard | C56: agillard1i@issuu.com | D56: +1 (419) 663-2236 | E56: 97490 Susan Avenue | F56: Toledo | G56: United States | H56: 43666 | I56: No
A57: 09960-34242-LZ | B57: Salomo Cushworth | D57: +1 (609) 409-7044 | E57: 44 Oneill Parkway | F57: Trenton | G57: United States | H57: 8650 | I57: No
A58: 04671-85591-RT | B58: Theda Grizard | C58: tgrizard1k@odnoklassniki.ru | D58: +1 (813) 243-2150 | E58: 6 Knutson Pass | F58: Tampa | G58: United States | H58: 33686 | I58: Yes
A59: 25729-68859-UA | B59: Rozele Relton | C59: rrelton1l@stanford.edu | D59: +1 (850) 626-1181 | E59: 2484 Reindahl Court | F59: Pensacola | G59: United States | H59: 32590 | I59: No
A60: 05501-86351-NX | B60: Willa Rolling | D60: +1 (813) 759-3534 | E60: 3 Mockingbird Plaza | F60: Zephyrhills | G60: United States | H60: 33543 | I60: Yes
A61: 04521-04300-OK | B61: Stanislaus Gilroy | C61: sgilroy1n@eepurl.com | E61: 9120 Harbort Terrace | F61: Saint Paul | G61: United States | H61: 55123 | I61: Yes
A62: 58689-55264-VK | B62: Correy Cottingham | C62: ccottingham1o@wikipedia.org | D62: +1 (260) 764-1820 | E62: 394 Logan Road | F62: Fort Wayne | G62: United States | H62: 46862 | I62: No
A63: 79436-73011-MM | B63: Pammi Endacott | D63: +44 (177) 260-5076 | E63: 5841 Atwood Lane | F63: Wootton | G63: United Kingdom | H63: NN4 | I63: Yes
A64: 65552-60476-KY | B64: Nona Linklater | D64: +1 (239) 347-9766 | E64: 856 Bonner Parkway | F64: Naples | G64: United States | H64: 34114 | I64: Yes
A65: 69904-02729-YS | B65: Annadiane Dykes | C65: adykes1r@eventbrite.com | D65: +1 (312) 111-6203 | E65: 31 Northport Terrace | F65: Chicago | G65: United States | H65: 60681 | I65: No
A66: 01433-04270-AX | B66: Felecia Dodgson | D66: +1 (973) 434-8662 | E66: 48053 8th Crossing | F66: Newark | G66: United States | H66: 7104 | I66: Yes
A67: 14204-14186-LA | B67: Angelia Cockrem | C67: acockrem1t@engadget.com | D67: +1 (571) 316-8217 | E67: 1 Sherman Alley | F67: Vienna | G67: United States | H67: 22184 | I67: Yes
A68: 32948-34398-HC | B68: Belvia Umpleby | C68: bumpleby1u@soundcloud.com | D68: +1 (682) 627-0888 | E68: 710 Prairie Rose Terrace | F68: Fort Worth | G68: United States | H68: 76178 | I68: Yes
A69: 77343-52608-FF | B69: Nat Saleway | C69: nsaleway1v@dedecms.com | D69: +1 (323) 473-0294 | E69: 0780 Anthes Plaza | F69: Burbank | G69: United States | H69: 91505 | I69: No
A70: 42770-36274-QA | B70: Hayward Goulter | C70: hgoulter1w@abc.net.au | D70: +1 (423) 764-7751 | E70: 2081 Mariners Cove Drive | F70: Kingsport | G70: United States | H70: 37665 | I70: No
A71: 14103-58987-ZU | B71: Gay Rizzello | C71: grizzello1x@symantec.com | D71: +44 (247) 225-8003 | E71: 21 Schmedeman Crossing | F71: Liverpool | G71: United Kingdom | H71: L33 | I71: Yes
A72: 69958-32065-SW | B72: Shannon List | C72: slist1y@mapquest.com | D72: +1 (614) 279-9816 | E72: 7123 Algoma Center | F72: Columbus | G72: United States | H72: 43231 | I72: No
A73: 69533-84907-FA | B73: Shirlene Edmondson | C73: sedmondson1z@theguardian.com | D73: +353 (248) 428-7978 | E73: 4752 International Point | F73: Newmarket on Fergus | G73: Ireland | H73: P17 | I73: No
A74: 76005-95461-CI | B74: Aurlie McCarl | D74: +1 (504) 209-2724 | E74: 731 David Park | F74: New Orleans | G74: United States | H74: 70183 | I74: No
A75: 15395-90855-VB | B75: Alikee Carryer | D75: +1 (704) 799-5219 | E75: 247 Helena Drive | F75: Charlotte | G75: United States | H75: 28230 | I75: Yes
A76: 80640-45811-LB | B76: Jennifer Rangall | C76: jrangall22@newsvine.com | D76: +1 (781) 512-6637 | E76: 0 Grasskamp Lane | F76: Springfield | G76: United States | H76: 1114 | I76: Yes
A77: 28476-04082-GR | B77: Kipper Boorn | C77: kboorn23@ezinearticles.com | D77: +353 (359) 134-1550 | E77: 9513 Meadow Ridge Parkway | F77: Listowel | G77: Ireland | H77: V31 | I77: Yes
A78: 12018-75670-EU | B78: Melania Beadle | D78: +353 (569) 458-9673 | E78: 4418 Quincy Terrace | F78: Moycullen | G78: Ireland | H78: A41 | I78: Yes
A79: 86437-17399-FK | B79: Colene Elgey | C79: celgey25@webs.com | D79: +1 (432) 261-0702 | E79: 45 Marcy Crossing | F79: Midland | G79: United States | H79: 79705 | I79: No
A80: 62979-53167-ML | B80: Lothaire Mizzi | C80: lmizzi26@rakuten.co.jp | D80: +1 (214) 719-8530 | E80: 74 Atwood Lane | F80: Dallas | G80: United States | H80: 75323 | I80: Yes
A81: 54810-81899-HL | B81: Cletis Giacomazzo | C81: cgiacomazzo27@jigsy.com | D81: +1 (571) 703-2064 | E81: 817 Ridgeway Hill | F81: Dulles | G81: United States | H81: 20189 | I81: No
A82: 26103-41504-IB | B82: Ami Arnow | C82: aarnow28@arizona.edu | D82: +1 (650) 238-1964 | E82: 12 Oakridge Court | F82: Oakland | G82: United States | H82: 94627 | I82: Yes
A83: 76534-45229-SG | B83: Sheppard Yann | C83: syann29@senate.gov | D83: +1 (719) 803-5276 | E83: 4 Farmco Place | F83: Colorado Springs | G83: United States | H83: 80930 | I83: Yes
A84: 81744-27332-RR | B84: Bunny Naulls | C84: bnaulls2a@tiny.cc | D84: +353 (809) 128-0755 | E84: 595 Melby Avenue | F84: Adare | G84: Ireland | H84: H54 | I84: Yes
A85: 91513-75657-PH | B85: Hally Lorait | D85: +1 (716) 869-3749 | E85: 80 Jana Avenue | F85: Buffalo | G85: United States | H85: 14205 | I85: Yes
A86: 30373-66619-CB | B86: Zaccaria Sherewood | C86: zsherewood2c@apache.org | D86: +1 (209) 433-7924 | E86: 1325 Jay Terrace | F86: Fresno | G86: United States | H86: 93715 | I86: No
A87: 31582-23562-FM | B87: Jeffrey Dufaire | C87: jdufaire2d@fc2.com | E87: 8 Buell Junction | F87: Fort Worth | G87: United States | H87: 76121 | I87: No
A88: 58638-01029-CB | B88: Blancha McAmish | C88: bmcamish2e@tripadvisor.com | E88: 5484 Stephen Court | F88: Oklahoma City | G88: United States | H88: 73179 | I88: Yes
A89: 81431-12577-VD | B89: Beitris Keaveney | C89: bkeaveney2f@netlog.com | E89: 67319 Redwing Parkway | F89: Beaumont | G89: United States | H89: 77705 | I89: No
A90: 68894-91205-MP | B90: Elna Grise | C90: egrise2g@cargocollective.com | E90: 92 Becker Circle | F90: Reno | G90: United States | H90: 89519 | I90: No
A91: 87602-55754-VN | B91: Torie Gottelier | C91: tgottelier2h@vistaprint.com | D91: +1 (816) 743-8492 | E91: 426 Division Avenue | F91: Kansas City | G91: United States | H91: 64136 | I91: No
A92: 39181-35745-WH | B92: Loydie Langlais | D92: +353 (576) 222-5069 | E92: 290 Ilene Street | F92: Crumlin | G92: Ireland | H92: D6W | I92: Yes
A93: 30381-64762-NG | B93: Adham Greenhead | C93: agreenhead2j@dailymail.co.uk | D93: +1 (951) 797-0738 | E93: 0062 Spenser Place | F93: Corona | G93: United States | H93: 92878 | I93: No
A94: 17503-27693-ZH | B94: Hamish MacSherry | D94: +1 (512) 430-4374 | E94: 7 Brentwood Plaza | F94: Austin | G94: United States | H94: 78759 | I94: Yes
A95: 89442-35633-HJ | B95: Else Langcaster | C95: elangcaster2l@spotify.com | D95: +44 (547) 590-3103 | E95: 3658 Jenna Street | F95: Normanton | G95: United Kingdom | H95: LE15 | I95: Yes
A96: 13654-85265-IL | B96: Rudy Farquharson | E96: 30178 Claremont Road | F96: Charlesland | G96: Ireland | H96: A63 | I96: Yes
A97: 40946-22090-FP | B97: Norene Magauran | C97: nmagauran2n@51.la | E97: 567 Artisan Place | F97: Fresno | G97: United States | H97: 93762 | I97: No
A98: 29050-93691-TS | B98: Vicki Kirdsch | C98: vkirdsch2o@google.fr | E98: 0263 Golf Street | F98: Saint Louis | G98: United States | H98: 63150 | I98: No
A99: 64395-74865-WF | B99: Ilysa Whapple | C99: iwhapple2p@com.com | D99: +1 (559) 522-1152 | E99: 41598 Everett Drive | F99: Fresno | G99: United States | H99: 93726 | I99: No
A100: 81861-66046-SU | B100: Ruy Cancellieri | D100: +353 (338) 743-8327 | E100: 251 Welch Parkway | F100: Confey | G100: Ireland | H100: A86 | I100: No
...

Sheet products
A1: Product ID | B1: Coffee Type | C1: Roast Type | D1: Size | E1: Unit Price | F1: Price per 100g | G1: Profit
A2: A-L-0.2 | B2: Ara | C2: L | D2: 0.2 | E2: 3.885 | F2: 1.9425 | G2: 0.34965
A3: A-L-0.5 | B3: Ara | C3: L | D3: 0.5 | E3: 7.77 | F3: 1.554 | G3: 0.6993
A4: A-L-1 | B4: Ara | C4: L | D4: 1 | E4: 12.95 | F4: 1.295 | G4: 1.1655
A5: A-L-2.5 | B5: Ara | C5: L | D5: 2.5 | E5: 29.785 | F5: 1.1914 | G5: 2.68065
A6: A-M-0.2 | B6: Ara | C6: M | D6: 0.2 | E6: 3.375 | F6: 1.6875 | G6: 0.30375
A7: A-M-0.5 | B7: Ara | C7: M | D7: 0.5 | E7: 6.75 | F7: 1.35 | G7: 0.6075
A8: A-M-1 | B8: Ara | C8: M | D8: 1 | E8: 11.25 | F8: 1.125 | G8: 1.0125
A9: A-M-2.5 | B9: Ara | C9: M | D9: 2.5 | E9: 25.875 | F9: 1.035 | G9: 2.32875
A10: A-D-0.2 | B10: Ara | C10: D | D10: 0.2 | E10: 2.985 | F10: 1.4925 | G10: 0.26865
A11: A-D-0.5 | B11: Ara | C11: D | D11: 0.5 | E11: 5.97 | F11: 1.194 | G11: 0.5373
A12: A-D-1 | B12: Ara | C12: D | D12: 1 | E12: 9.95 | F12: 0.995 | G12: 0.8955
A13: A-D-2.5 | B13: Ara | C13: D | D13: 2.5 | E13: 22.885 | F13: 0.9154 | G13: 2.05965
... A49: E-D-2.5 | B49: Exc | C49: D | D49: 2.5 | E49: 27.945 | F49: 1.1178 | G49: 3.07395

Sheet Combined table
A1: Order Date | B1: Product ID | C1: Quantity | D1: Customer Name | E1: City | F1: Country | G1: Loyalty Card | H1: Coffee Type | I1: Roast Type | J1: Size | K1: Unite Price | L1: Price per 100g | M1: Profit | N1: Month-Year | O1: Revenue
A2: 43713 | B2: R-M-1 | C2: 2 | D2: Aloisia Allner | E2: Paterson | F2: United States | G2: Yes | H2: =VLOOKUP('Combined table'!B2,products!$A$1:$G$49,2,FALSE) -> Rob | I2: =VLOOKUP('Combined table'!B2,products!$A$1:$G$49,3,FALSE) -> M | J2: =VLOOKUP('Combined table'!B2,products!$A$1:$G$49,4,FALSE) -> 1 | K2: =VLOOKUP('Combined table'!B2,products!$A$1:$G$49,5,FALSE) -> 9.95 | L2: =VLOOKUP('Combined table'!B2,products!$A$1:$G$49,6,FALSE) -> 0.995 | M2: =VLOOKUP('Combined table'!B2,products!$A$1:$G$49,7,FALSE) -> 0.597 | N2: =TEXT(A2,"mmm yyyy") -> Sep 2019 | O2: =C2*K2 -> 19.9
A3: 43713 | B3: E-M-0.5 | C3: 5 | D3: Piotr Bote | E3: Crumlin | F3: Ireland | G3: No | H3: =VLOOKUP('Combined table'!B3,products!$A$1:$G$49,2,FALSE) -> Exc | I3: =VLOOKUP('Combined table'!B3,products!$A$1:$G$49,3,FALSE) -> M | J3: =VLOOKUP('Combined table'!B3,products!$A$1:$G$49,4,FALSE) -> 0.5 | K3: =VLOOKUP('Combined table'!B3,products!$A$1:$G$49,5,FALSE) -> 8.25 | L3: =VLOOKUP('Combined table'!B3,products!$A$1:$G$49,6,FALSE) -> 1.65 | M3: =VLOOKUP('Combined table'!B3,products!$A$1:$G$49,7,FALSE) -> 0.9075 | N3: =TEXT(A3,"mmm yyyy") -> Sep 2019 | O3: =C3*K3 -> 41.25
A4: 44364 | B4: A-L-1 | C4: 1 | D4: Jami Redholes | E4: San Antonio | F4: United States | G4: Yes | H4: =VLOOKUP('Combined table'!B4,products!$A$1:$G$49,2,FALSE) -> Ara | I4: =VLOOKUP('Combined table'!B4,products!$A$1:$G$49,3,FALSE) -> L | J4: =VLOOKUP('Combined table'!B4,products!$A$1:$G$49,4,FALSE) -> 1 | K4: =VLOOKUP('Combined table'!B4,products!$A$1:$G$49,5,FALSE) -> 12.95 | L4: =VLOOKUP('Combined table'!B4,products!$A$1:$G$49,6,FALSE) -> 1.295 | M4: =VLOOKUP('Combined table'!B4,products!$A$1:$G$49,7,FALSE) -> 1.1655 | N4: =TEXT(A4,"mmm yyyy") -> Jun 2021 | O4: =C4*K4 -> 12.95
A5: 44392 | B5: E-M-1 | C5: 2 | D5: Dene Azema | E5: Springfield | F5: United States | G5: Yes | H5: =VLOOKUP('Combined table'!B5,products!$A$1:$G$49,2,FALSE) -> Exc | I5: =VLOOKUP('Combined table'!B5,products!$A$1:$G$49,3,FALSE) -> M | J5: =VLOOKUP('Combined table'!B5,products!$A$1:$G$49,4,FALSE) -> 1 | K5: =VLOOKUP('Combined table'!B5,products!$A$1:$G$49,5,FALSE) -> 13.75 | L5: =VLOOKUP('Combined table'!B5,products!$A$1:$G$49,6,FALSE) -> 1.375 | M5: =VLOOKUP('Combined table'!B5,products!$A$1:$G$49,7,FALSE) -> 1.5125 | N5: =TEXT(A5,"mmm yyyy") -> Jul 2021 | O5: =C5*K5 -> 27.5
A6: 44392 | B6: R-L-2.5 | C6: 2 | D6: Christoffer O' Shea | E6: Cill Airne | F6: Ireland | G6: No | H6: =VLOOKUP('Combined table'!B6,products!$A$1:$G$49,2,FALSE) -> Rob | I6: =VLOOKUP('Combined table'!B6,products!$A$1:$G$49,3,FALSE) -> L | J6: =VLOOKUP('Combined table'!B6,products!$A$1:$G$49,4,FALSE) -> 2.5 | K6: =VLOOKUP('Combined table'!B6,products!$A$1:$G$49,5,FALSE) -> 27.485 | L6: =VLOOKUP('Combined table'!B6,products!$A$1:$G$49,6,FALSE) -> 1.0994 | M6: =VLOOKUP('Combined table'!B6,products!$A$1:$G$49,7,FALSE) -> 1.6491 | N6: =TEXT(A6,"mmm yyyy") -> Jul 2021 | O6: =C6*K6 -> 54.97
A7: 44412 | B7: L-D-1 | C7: 3 | D7: Beryle Cottier | E7: Scranton | F7: United States | G7: No | H7: =VLOOKUP('Combined table'!B7,products!$A$1:$G$49,2,FALSE) -> Lib | I7: =VLOOKUP('Combined table'!B7,products!$A$1:$G$49,3,FALSE) -> D | J7: =VLOOKUP('Combined table'!B7,products!$A$1:$G$49,4,FALSE) -> 1 | K7: =VLOOKUP('Combined table'!B7,products!$A$1:$G$49,5,FALSE) -> 12.95 | L7: =VLOOKUP('Combined table'!B7,products!$A$1:$G$49,6,FALSE) -> 1.295 | M7: =VLOOKUP('Combined table'!B7,products!$A$1:$G$49,7,FALSE) -> 1.6835 | N7: =TEXT(A7,"mmm yyyy") -> Aug 2021 | O7: =C7*K7 -> 38.85
A8: 44582 | B8: E-D-0.5 | C8: 3 | D8: Shaylynn Lobe | E8: Dayton | F8: United States | G8: Yes | H8: =VLOOKUP('Combined table'!B8,products!$A$1:$G$49,2,FALSE) -> Exc | I8: =VLOOKUP('Combined table'!B8,products!$A$1:$G$49,3,FALSE) -> D | J8: =VLOOKUP('Combined table'!B8,products!$A$1:$G$49,4,FALSE) -> 0.5 | K8: =VLOOKUP('Combined table'!B8,products!$A$1:$G$49,5,FALSE) -> 7.29 | L8: =VLOOKUP('Combined table'!B8,products!$A$1:$G$49,6,FALSE) -> 1.458 | M8: =VLOOKUP('Combined table'!B8,products!$A$1:$G$49,7,FALSE) -> 0.8019 | N8: =TEXT(A8,"mmm yyyy") -> Jan 2022 | O8: =C8*K8 -> 21.87
A9: 44701 | B9: L-L-0.2 | C9: 1 | D9: Melvin Wharfe | E9: Kill | F9: Ireland | G9: Yes | H9: =VLOOKUP('Combined table'!B9,products!$A$1:$G$49,2,FALSE) -> Lib | I9: =VLOOKUP('Combined table'!B9,products!$A$1:$G$49,3,FALSE) -> L | J9: =VLOOKUP('Combined table'!B9,products!$A$1:$G$49,4,FALSE) -> 0.2 | K9: =VLOOKUP('Combined table'!B9,products!$A$1:$G$49,5,FALSE) -> 4.755 | L9: =VLOOKUP('Combined table'!B9,products!$A$1:$G$49,6,FALSE) -> 2.3775 | M9: =VLOOKUP('Combined table'!B9,products!$A$1:$G$49,7,FALSE) -> 0.61815 | N9: =TEXT(A9,"mmm yyyy") -> May 2022 | O9: =C9*K9 -> 4.755
A10: 43467 | B10: R-M-0.5 | C10: 3 | D10: Guthrey Petracci | E10: Los Angeles | F10: United States | G10: No | H10: =VLOOKUP('Combined table'!B10,products!$A$1:$G$49,2,FALSE) -> Rob | I10: =VLOOKUP('Combined table'!B10,products!$A$1:$G$49,3,FALSE) -> M | J10: =VLOOKUP('Combined table'!B10,products!$A$1:$G$49,4,FALSE) -> 0.5 | K10: =VLOOKUP('Combined table'!B10,products!$A$1:$G$49,5,FALSE) -> 5.97 | L10: =VLOOKUP('Combined table'!B10,products!$A$1:$G$49,6,FALSE) -> 1.194 | M10: =VLOOKUP('Combined table'!B10,products!$A$1:$G$49,7,FALSE) -> 0.3582 | N10: =TEXT(A10,"mmm yyyy") -> Jan 2019 | O10: =C10*K10 -> 17.91
A11: 43713 | B11: R-M-0.5 | C11: 1 | D11: Rodger Raven | E11: Los Angeles | F11: United States | G11: No | H11: =VLOOKUP('Combined table'!B11,products!$A$1:$G$49,2,FALSE) -> Rob | I11: =VLOOKUP('Combined table'!B11,products!$A$1:$G$49,3,FALSE) -> M | J11: =VLOOKUP('Combined table'!B11,products!$A$1:$G$49,4,FALSE) -> 0.5 | K11: =VLOOKUP('Combined table'!B11,products!$A$1:$G$49,5,FALSE) -> 5.97 | L11: =VLOOKUP('Combined table'!B11,products!$A$1:$G$49,6,FALSE) -> 1.194 | M11: =VLOOKUP('Combined table'!B11,products!$A$1:$G$49,7,FALSE) -> 0.3582 | N11: =TEXT(A11,"mmm yyyy") -> Sep 2019 | O11: =C11*K11 -> 5.97
A12: 44263 | B12: A-D-1 | C12: 4 | D12: Ferrell Ferber | E12: San Jose | F12: United States | G12: No | H12: =VLOOKUP('Combined table'!B12,products!$A$1:$G$49,2,FALSE) -> Ara | I12: =VLOOKUP('Combined table'!B12,products!$A$1:$G$49,3,FALSE) -> D | J12: =VLOOKUP('Combined table'!B12,products!$A$1:$G$49,4,FALSE) -> 1 | K12: =VLOOKUP('Combined table'!B12,products!$A$1:$G$49,5,FALSE) -> 9.95 | L12: =VLOOKUP('Combined table'!B12,products!$A$1:$G$49,6,FALSE) -> 0.995 | M12: =VLOOKUP('Combined table'!B12,products!$A$1:$G$49,7,FALSE) -> 0.8955 | N12: =TEXT(A12,"mmm yyyy") -> Mar 2021 | O12: =C12*K12 -> 39.8
A13: 44132 | B13: E-L-2.5 | C13: 5 | D13: Duky Phizackerly | E13: San Jose | F13: United States | G13: Yes | H13: =VLOOKUP('Combined table'!B13,products!$A$1:$G$49,2,FALSE) -> Exc | I13: =VLOOKUP('Combined table'!B13,products!$A$1:$G$49,3,FALSE) -> L | J13: =VLOOKUP('Combined table'!B13,products!$A$1:$G$49,4,FALSE) -> 2.5 | K13: =VLOOKUP('Combined table'!B13,products!$A$1:$G$49,5,FALSE) -> 34.155 | L13: =VLOOKUP('Combined table'!B13,products!$A$1:$G$49,6,FALSE) -> 1.3662 | M13: =VLOOKUP('Combined table'!B13,products!$A$1:$G$49,7,FALSE) -> 3.75705 | N13: =TEXT(A13,"mmm yyyy") -> Oct 2020 | O13: =C13*K13 -> 170.775
... A20: 43629 | B20: R-D-2.5 | C20: 4 | D20: Pall Redford | E20: Caherconlish | F20: Ireland | G20: Yes | H20: =VLOOKUP('Combined table'!B20,products!$A$1:$G$49,2,FALSE) -> Rob | I20: =VLOOKUP('Combined table'!B20,products!$A$1:$G$49,3,FALSE) -> D | J20: =VLOOKUP('Combined table'!B20,products!$A$1:$G$49,4,FALSE) -> 2.5 | K20: =VLOOKUP('Combined table'!B20,products!$A$1:$G$49,5,FALSE) -> 20.585 | L20: =VLOOKUP('Combined table'!B20,products!$A$1:$G$49,6,FALSE) -> 0.8234 | M20: =VLOOKUP('Combined table'!B20,products!$A$1:$G$49,7,FALSE) -> 1.2351 | N20: =TEXT(A20,"mmm yyyy") -> Jun 2019 | O20: =C20*K20 -> 82.34
A21: 44169 | B21: A-M-0.2 | C21: 5 | D21: Aurea Corradino | E21: New York City | F21: United States | G21: Yes | H21: =VLOOKUP('Combined table'!B21,products!$A$1:$G$49,2,FALSE) -> Ara | I21: =VLOOKUP('Combined table'!B21,products!$A$1:$G$49,3,FALSE) -> M | J21: =VLOOKUP('Combined table'!B21,products!$A$1:$G$49,4,FALSE) -> 0.2 | K21: =VLOOKUP('Combined table'!B21,products!$A$1:$G$49,5,FALSE) -> 3.375 | L21: =VLOOKUP('Combined table'!B21,products!$A$1:$G$49,6,FALSE) -> 1.6875 | M21: =VLOOKUP('Combined table'!B21,products!$A$1:$G$49,7,FALSE) -> 0.30375 | N21: =TEXT(A21,"mmm yyyy") -> Dec 2020 | O21: =C21*K21 -> 16.875 | Q21: Correlattion | R21: =CORREL(O:O,M:M) -> 0.70657726
A22: 44169 | B22: E-D-0.2 | C22: 4 | D22: Kendal Scardefield | E22: Clondalkin | F22: Ireland | G22: Yes | H22: =VLOOKUP('Combined table'!B22,products!$A$1:$G$49,2,FALSE) -> Exc | I22: =VLOOKUP('Combined table'!B22,products!$A$1:$G$49,3,FALSE) -> D | J22: =VLOOKUP('Combined table'!B22,products!$A$1:$G$49,4,FALSE) -> 0.2 | K22: =VLOOKUP('Combined table'!B22,products!$A$1:$G$49,5,FALSE) -> 3.645 | L22: =VLOOKUP('Combined table'!B22,products!$A$1:$G$49,6,FALSE) -> 1.8225 | M22: =VLOOKUP('Combined table'!B22,products!$A$1:$G$49,7,FALSE) -> 0.40095 | N22: =TEXT(A22,"mmm yyyy") -> Dec 2020 | O22: =C22*K22 -> 14.58
A23: 44169 | B23: A-D-0.2 | C23: 6 | D23: Avrit Davidowsky | E23: Grand Rapids | F23: United States | G23: No | H23: =VLOOKUP('Combined table'!B23,products!$A$1:$G$49,2,FALSE) -> Ara | I23: =VLOOKUP('Combined table'!B23,products!$A$1:$G$49,3,FALSE) -> D | J23: =VLOOKUP('Combined table'!B23,products!$A$1:$G$49,4,FALSE) -> 0.2 | K23: =VLOOKUP('Combined table'!B23,products!$A$1:$G$49,5,FALSE) -> 2.985 | L23: =VLOOKUP('Combined table'!B23,products!$A$1:$G$49,6,FALSE) -> 1.4925 | M23: =VLOOKUP('Combined table'!B23,products!$A$1:$G$49,7,FALSE) -> 0.26865 | N23: =TEXT(A23,"mmm yyyy") -> Dec 2020 | O23: =C23*K23 -> 17.91
A24: 44218 | B24: R-M-2.5 | C24: 4 | D24: Annabel Antuk | E24: Punta Gorda | F24: United States | G24: Yes | H24: =VLOOKUP('Combined table'!B24,products!$A$1:$G$49,2,FALSE) -> Rob | I24: =VLOOKUP('Combined table'!B24,products!$A$1:$G$49,3,FALSE) -> M | J24: =VLOOKUP('Combined table'!B24,products!$A$1:$G$49,4,FALSE) -> 2.5 | K24: =VLOOKUP('Combined table'!B24,products!$A$1:$G$49,5,FALSE) -> 22.885 | L24: =VLOOKUP('Combined table'!B24,products!$A$1:$G$49,6,FALSE) -> 0.9154 | M24: =VLOOKUP('Combined table'!B24,products!$A$1:$G$49,7,FALSE) -> 1.3731 | N24: =TEXT(A24,"mmm yyyy") -> Jan 2021 | O24: =C24*K24 -> 91.54
A25: 44603 | B25: A-D-0.2 | C25: 4 | D25: Iorgo Kleinert | E25: Vancouver | F25: United States | G25: Yes | H25: =VLOOKUP('Combined table'!B25,products!$A$1:$G$49,2,FALSE) -> Ara | I25: =VLOOKUP('Combined table'!B25,products!$A$1:$G$49,3,FALSE) -> D | J25: =VLOOKUP('Combined table'!B25,products!$A$1:$G$49,4,FALSE) -> 0.2 | K25: =VLOOKUP('Combined table'!B25,products!$A$1:$G$49,5,FALSE) -> 2.985 | L25: =VLOOKUP('Combined table'!B25,products!$A$1:$G$49,6,FALSE) -> 1.4925 | M25: =VLOOKUP('Combined table'!B25,products!$A$1:$G$49,7,FALSE) -> 0.26865 | N25: =TEXT(A25,"mmm yyyy") -> Feb 2022 | O25: =C25*K25 -> 11.94
A26: 44454 | B26: A-M-1 | C26: 1 | D26: Chrisy Blofeld | E26: Englewood | F26: United States | G26: No | H26: =VLOOKUP('Combined table'!B26,products!$A$1:$G$49,2,FALSE) -> Ara | I26: =VLOOKUP('Combined table'!B26,products!$A$1:$G$49,3,FALSE) -> M | J26: =VLOOKUP('Combined table'!B26,products!$A$1:$G$49,4,FALSE) -> 1 | K26: =VLOOKUP('Combined table'!B26,products!$A$1:$G$49,5,FALSE) -> 11.25 | L26: =VLOOKUP('Combined table'!B26,products!$A$1:$G$49,6,FALSE) -> 1.125 | M26: =VLOOKUP('Combined table'!B26,products!$A$1:$G$49,7,FALSE) -> 1.0125 | N26: =TEXT(A26,"mmm yyyy") -> Sep 2021 | O26: =C26*K26 -> 11.25
A27: 44128 | B27: E-M-0.2 | C27: 3 | D27: Culley Farris | E27: Punta Gorda | F27: United States | G27: Yes | H27: =VLOOKUP('Combined table'!B27,products!$A$1:$G$49,2,FALSE) -> Exc | I27: =VLOOKUP('Combined table'!B27,products!$A$1:$G$49,3,FALSE) -> M | J27: =VLOOKUP('Combined table'!B27,products!$A$1:$G$49,4,FALSE) -> 0.2 | K27: =VLOOKUP('Combined table'!B27,products!$A$1:$G$49,5,FALSE) -> 4.125 | L27: =VLOOKUP('Combined table'!B27,products!$A$1:$G$49,6,FALSE) -> 2.0625 | M27: =VLOOKUP('Combined table'!B27,products!$A$1:$G$49,7,FALSE) -> 0.45375 | N27: =TEXT(A27,"mmm yyyy") -> Oct 2020 | O27: =C27*K27 -> 12.375
A28: 43516 | B28: A-M-0.5 | C28: 4 | D28: Selene Shales | E28: Petaluma | F28: United States | G28: Yes | H28: =VLOOKUP('Combined table'!B28,products!$A$1:$G$49,2,FALSE) -> Ara | I28: =VLOOKUP('Combined table'!B28,products!$A$1:$G$49,3,FALSE) -> M | J28: =VLOOKUP('Combined table'!B28,products!$A$1:$G$49,4,FALSE) -> 0.5 | K28: =VLOOKUP('Combined table'!B28,products!$A$1:$G$49,5,FALSE) -> 6.75 | L28: =VLOOKUP('Combined table'!B28,products!$A$1:$G$49,6,FALSE) -> 1.35 | M28: =VLOOKUP('Combined table'!B28,products!$A$1:$G$49,7,FALSE) -> 0.6075 | N28: =TEXT(A28,"mmm yyyy") -> Feb 2019 | O28: =C28*K28 -> 27
A29: 43746 | B29: A-M-0.2 | C29: 5 | D29: Vivie Danneil | E29: Tralee | F29: Ireland | G29: No | H29: =VLOOKUP('Combined table'!B29,products!$A$1:$G$49,2,FALSE) -> Ara | I29: =VLOOKUP('Combined table'!B29,products!$A$1:$G$49,3,FALSE) -> M | J29: =VLOOKUP('Combined table'!B29,products!$A$1:$G$49,4,FALSE) -> 0.2 | K29: =VLOOKUP('Combined table'!B29,products!$A$1:$G$49,5,FALSE) -> 3.375 | L29: =VLOOKUP('Combined table'!B29,products!$A$1:$G$49,6,FALSE) -> 1.6875 | M29: =VLOOKUP('Combined table'!B29,products!$A$1:$G$49,7,FALSE) -> 0.30375 | N29: =TEXT(A29,"mmm yyyy") -> Oct 2019 | O29: =C29*K29 -> 16.875
A30: 44775 | B30: A-D-0.5 | C30: 3 | D30: Theresita Newbury | E30: Clonskeagh | F30: Ireland | G30: No | H30: =VLOOKUP('Combined table'!B30,products!$A$1:$G$49,2,FALSE) -> Ara | I30: =VLOOKUP('Combined table'!B30,products!$A$1:$G$49,3,FALSE) -> D | J30: =VLOOKUP('Combined table'!B30,products!$A$1:$G$49,4,FALSE) -> 0.5 | K30: =VLOOKUP('Combined table'!B30,products!$A$1:$G$49,5,FALSE) -> 5.97 | L30: =VLOOKUP('Combined table'!B30,products!$A$1:$G$49,6,FALSE) -> 1.194 | M30: =VLOOKUP('Combined table'!B30,products!$A$1:$G$49,7,FALSE) -> 0.5373 | N30: =TEXT(A30,"mmm yyyy") -> Aug 2022 | O30: =C30*K30 -> 17.91
A31: 43516 | B31: A-D-1 | C31: 4 | D31: Mozelle Calcutt | E31: Rathwire | F31: Ireland | G31: Yes | H31: =VLOOKUP('Combined table'!B31,products!$A$1:$G$49,2,FALSE) -> Ara | I31: =VLOOKUP('Combined table'!B31,products!$A$1:$G$49,3,FALSE) -> D | J31: =VLOOKUP('Combined table'!B31,products!$A$1:$G$49,4,FALSE) -> 1 | K31: =VLOOKUP('Combined table'!B31,products!$A$1:$G$49,5,FALSE) -> 9.95 | L31: =VLOOKUP('Combined table'!B31,products!$A$1:$G$49,6,FALSE) -> 0.995 | M31: =VLOOKUP('Combined table'!B31,products!$A$1:$G$49,7,FALSE) -> 0.8955 | N31: =TEXT(A31,"mmm yyyy") -> Feb 2019 | O31: =C31*K31 -> 39.8
A32: 44464 | B32: L-M-0.2 | C32: 5 | D32: Adrian Swaine | E32: Aurora | F32: United States | G32: No | H32: =VLOOKUP('Combined table'!B32,products!$A$1:$G$49,2,FALSE) -> Lib | I32: =VLOOKUP('Combined table'!B32,products!$A$1:$G$49,3,FALSE) -> M | J32: =VLOOKUP('Combined table'!B32,products!$A$1:$G$49,4,FALSE) -> 0.2 | K32: =VLOOKUP('Combined table'!B32,products!$A$1:$G$49,5,FALSE) -> 4.365 | L32: =VLOOKUP('Combined table'!B32,products!$A$1:$G$49,6,FALSE) -> 2.1825 | M32: =VLOOKUP('Combined table'!B32,products!$A$1:$G$49,7,FALSE) -> 0.56745 | N32: =TEXT(A32,"mmm yyyy") -> Sep 2021 | O32: =C32*K32 -> 21.825
A33: 44464 | B33: A-D-0.5 | C33: 6 | D33: Ray Leivesley | E33: Jamaica | F33: United States | G33: No | H33: =VLOOKUP('Combined table'!B33,products!$A$1:$G$49,2,FALSE) -> Ara | I33: =VLOOKUP('Combined table'!B33,products!$A$1:$G$49,3,FALSE) -> D | J33: =VLOOKUP('Combined table'!B33,products!$A$1:$G$49,4,FALSE) -> 0.5 | K33: =VLOOKUP('Combined table'!B33,products!$A$1:$G$49,5,FALSE) -> 5.97 | L33: =VLOOKUP('Combined table'!B33,products!$A$1:$G$49,6,FALSE) -> 1.194 | M33: =VLOOKUP('Combined table'!B33,products!$A$1:$G$49,7,FALSE) -> 0.5373 | N33: =TEXT(A33,"mmm yyyy") -> Sep 2021 | O33: =C33*K33 -> 35.82
... A1001: 44119 | B1001: E-M-0.2 | C1001: 3 | D1001: Vidovic Antonelli | E1001: London | F1001: United Kingdom | G1001: Yes | H1001: =VLOOKUP('Combined table'!B1001,products!$A$1:$G$49,2,FALSE) -> Exc | I1001: =VLOOKUP('Combined table'!B1001,products!$A$1:$G$49,3,FALSE) -> M | J1001: =VLOOKUP('Combined table'!B1001,products!$A$1:$G$49,4,FALSE) -> 0.2 | K1001: =VLOOKUP('Combined table'!B1001,products!$A$1:$G$49,5,FALSE) -> 4.125 | L1001: =VLOOKUP('Combined table'!B1001,products!$A$1:$G$49,6,FALSE) -> 2.0625 | M1001: =VLOOKUP('Combined table'!B1001,products!$A$1:$G$49,7,FALSE) -> 0.45375 | N1001: =TEXT(A1001,"mmm yyyy") -> Oct 2020 | O1001: =C1001*K1001 -> 12.375

Sheet Year-month
C4: Year | D4: Jan | E4: Feb | F4: Mar | G4: Apr | H4: May | I4: Jun | J4: Jul | K4: Aug | L4: Sep | M4: Oct | N4: Nov | O4: Dec
C5: 2019 | D5: 828.985 | E5: 987.405 | F5: 1021.14 | G5: 1680.75 | H5: 398.565 | I5: 1384.68 | J5: 1004.135 | K5: 706.345 | L5: 1277.02 | M5: 884.97 | N5: 823.385 | O5: 1189.785
C6: 2020 | D6: 566.95 | E6: 1798.34 | F6: 914.79 | G6: 761.81 | H6: 939.355 | I6: 1438.44 | J6: 1308.945 | K6: 300.4 | L6: 713.05 | M6: 1514.705 | N6: 1108.865 | O6: 751.895
C7: 2021 | D7: 837.685 | E7: 958.83 | F7: 1544.64 | G7: 1005.585 | H7: 907.69 | I7: 864.53 | J7: 763.105 | K7: 1075.91 | L7: 1643.575 | M7: 1400.4 | N7: 1616.18 | O7: 1147.98
C8: 2022 | D8: 1269.415 | E8: 393.63 | F8: 1315.205 | G8: 776.45 | H8: 1002.37 | I8: 1155.39 | J8: 906.73 | K8: 244.245 | L8: 0 | M8: 0 | N8: 0 | O8: 0

Sheet Sheet7
A3: Row Labels | B3: Sum of Revenue
A4: Apr 2019 | B4: 1680.75
A5: Apr 2020 | B5: 761.81
A6: Apr 2021 | B6: 1005.585
A7: Apr 2022 | B7: 776.45
A8: Aug 2019 | B8: 706.345
A9: Aug 2020 | B9: 300.4
A10: Aug 2021 | B10: 1075.91
A11: Aug 2022 | B11: 244.245
A12: Dec 2019 | B12: 1189.785
A13: Dec 2020 | B13: 751.895
A14: Dec 2021 | B14: 1147.98
A15: Feb 2019 | B15: 987.405
... A48: Grand Total | B48: 45134.255

Sheet Sheet7 (2)
A1: Row Labels | B1: Sum of Revenue
A2: Ara | B2: 11768.495
A3: Exc | B3: 12306.44
A4: Lib | B4: 12054.075
A5: Rob | B5: 9005.245
A6: Grand Total | B6: 45134.255

Sheet Sheet7 (3)
A1: Row Labels | B1: Sum of Revenue
A2: D | B2: 13179.315
A3: L | B3: 17354.465
A4: M | B4: 14600.475
A5: Grand Total | B5: 45134.255

Sheet Sheet7 (4)
B1: Column Labels
B2: 0.2 | C2: 0.5 | D2: 1 | E2: 2.5 | F2: Grand Total
A3: Sum of Revenue | B3: 3307.95 | C3: 7029.99 | D3: 11010.75 | E3: 23785.565 | F3: 45134.255

Sheet Sheet7 (5)
A1: Row Labels | B1: Sum of Revenue
A2: Ireland | B2: 6563.07
A3: United Kingdom | B3: 2661.5
A4: United States | B4: 35909.685
A5: Grand Total | B5: 45134.255

Sheet Sheet7 (6)
A1: Row Labels | B1: Sum of Revenue
A2: No | B2: 23979.77
A3: Yes | B3: 21154.485
A4: Grand Total | B4: 45134.255

Sheet Sheet7 (7)
A1: Row Labels | B1: Sum of Revenue
A2: Alexa Sizey | B2: 218.73
A3: Lacee Tanti | B3: 204.93
A4: Shelli Keynd | B4: 204.93
A5: Nanny Lush | B5: 204.93
A6: Daniel Heinonen | B6: 204.93
A7: Elysee Sketch | B7: 204.93
A8: Teddi Crowthe | B8: 204.93
A9: Lemuel Rignold | B9: 200.79
A10: Claudetta Rushe | B10: 189.75
A11: Hatty Dovydenas | B11: 189.75
A12: Grand Total | B12: 2028.6

Sheet Sheet7 (8)

Sheet Sheet16
